[
  {
    "id": 1,
    "images": [
      "images/chest/flat.png",
      "images/chest/chest.png"
    ],
    "muscle": "Chest",
    "category": "Middle Chest",
    "exerciseName": "Flat Bench Barbell Press",
    "alternative_id": [],
    "targetMuscle": "Middle Chest",
    "type": "Strength",
    "sets": 4,
    "reps": "8",
    "restTime": "90 sec",
    "compoundMovement": "Compound"
  },
  {
    "id": 2,
    "images": [
      "images/arms/biceps.png"
    ],
    "muscle": "Biceps",
    "category": "Short Head",
    "exerciseName": "Dumbbell Bicep Curls",
    "alternative_id": [],
    "targetMuscle": "Short Head",
    "type": "Hypertrophy",
    "sets": 4,
    "reps": "12",
    "restTime": "80 sec",
    "compoundMovement": "Compound"
  },
  {
    "id": 3,
    "images": [
      ""
    ],
    "muscle": "Biceps",
    "category": "Long Short Head",
    "exerciseName": "Barbbell curls shoulder wide",
    "alternative_id": [
      2
    ],
    "targetMuscle": "Short | Long Head",
    "type": "Hypertrophy",
    "sets": 4,
    "reps": "12",
    "restTime": "80 sec",
    "compoundMovement": "isolation"
  },
  {
    "id": 4,
    "images": [
      ""
    ],
    "muscle": "Biceps",
    "category": "Short Head",
    "exerciseName": "Barbbell curls Wide Grip",
    "alternative_id": [
      2,
      3
    ],
    "targetMuscle": "Short Head",
    "type": "Hypertrophy",
    "sets": 4,
    "reps": "12",
    "restTime": "80 sec",
    "compoundMovement": "isolation"
  },
  {
    "id": 5,
    "images": [
      "images/arms/triceps.png",
      "images/arms/triceps_2.png"
    ],
    "muscle": "Triceps",
    "category": "Long Head",
    "exerciseName": "Overhead Dumbbell Extension",
    "alternative_id": [],
    "targetMuscle": "Long Head",
    "type": "Hypertrophy",
    "sets": 4,
    "reps": "12",
    "restTime": "80 sec",
    "compoundMovement": "Compound"
  },
  {
    "id": 6,
    "images": [
      ""
    ],
    "muscle": "Biceps",
    "category": "Short Head",
    "exerciseName": "Supination Dumbbell Curls",
    "alternative_id": [
      4,
      2
    ],
    "targetMuscle": "Short Head",
    "type": "Hypertrophy",
    "sets": 4,
    "reps": "12",
    "restTime": "80 sec",
    "compoundMovement": "isolation"
  },
  {
    "id": 7,
    "images": [
      "images/back/image.png"
    ],
    "muscle": "Back",
    "category": "Lats",
    "exerciseName": "Lat pulldown",
    "alternative_id": [],
    "targetMuscle": "Lats",
    "type": "Hypertrophy",
    "sets": 4,
    "reps": "12",
    "restTime": "90",
    "compoundMovement": "isolation"
  }
]